pybullet_rendering/__init__.py
pybullet_rendering/plugin.py
pybullet_rendering/bindings.cpython-38-x86_64-linux-gnu.so
pybullet_rendering/examples/__init__.py
pybullet_rendering/examples/performance.py
pybullet_rendering/examples/panda3d_gui.py
pybullet_rendering/render/pyrender.py
pybullet_rendering/render/__init__.py
pybullet_rendering/render/panda3d.py
pybullet_rendering/render/utils.py
tests/__init__.py
tests/bingings/base_test_case.py
tests/bingings/test_scene_state.py
tests/bingings/__init__.py
tests/bingings/test_frame.py
tests/bingings/test_plugin.py
tests/bingings/test_scene_graph.py
tests/bingings/test_scene_view.py
pybullet_rendering-0.6.3.dist-info/RECORD
pybullet_rendering-0.6.3.dist-info/LICENSE
pybullet_rendering-0.6.3.dist-info/top_level.txt
pybullet_rendering-0.6.3.dist-info/METADATA
pybullet_rendering-0.6.3.dist-info/WHEEL
