Metadata-Version: 2.1
Name: pybullet-rendering
Version: 0.6.3
Summary: External rendering plugin for PyBullet
Home-page: https://github.com/ikalevatykh/pybullet_rendering
Author: Igor Kalevatykh
Author-email: kalevatykhia@gmail.com
License: GPL-3.0
Keywords: rendering graphics 3d visualization simulation
Platform: UNKNOWN
Classifier: Development Status :: 4 - Beta
Classifier: License :: OSI Approved :: GNU General Public License v3 (GPLv3)
Classifier: Operating System :: POSIX :: Linux
Classifier: Programming Language :: Python :: 3
Classifier: Programming Language :: Python :: Implementation :: CPython
Classifier: Topic :: Scientific/Engineering
Requires-Dist: numpy
Requires-Dist: pybullet (>=3.0.8)
